py2b/__init__.py
py2b/listCheck.py
py2b/playerInfo.py
py2b/serverInfo.py
py2b/singleCheck.py
2b2t.py-1.7.6.dist-info/LICENSE
2b2t.py-1.7.6.dist-info/METADATA
2b2t.py-1.7.6.dist-info/WHEEL
2b2t.py-1.7.6.dist-info/top_level.txt
2b2t.py-1.7.6.dist-info/RECORD
