Metadata-Version: 2.1
Name: 2b2t.py
Version: 1.7.6
Summary: A package for all things 2b2t
Home-page: https://github.com/BGP0/2b2t.py
Author: BGP and SkilzMastr
License: UNKNOWN
Platform: UNKNOWN
Classifier: Programming Language :: Python :: 3
Classifier: License :: OSI Approved :: MIT License
Classifier: Operating System :: OS Independent
Requires-Python: >=3.6
